aliyunsdkiotcc/__init__.py
aliyunsdkiotcc/request/__init__.py
aliyunsdkiotcc/request/v20210513/AddCidrToConnectionPoolRequest.py
aliyunsdkiotcc/request/v20210513/AddIoTCloudConnectorToGroupRequest.py
aliyunsdkiotcc/request/v20210513/AssociateIpWithConnectionPoolRequest.py
aliyunsdkiotcc/request/v20210513/AssociateVSwitchWithIoTCloudConnectorRequest.py
aliyunsdkiotcc/request/v20210513/ConfirmIoTCloudConnectorRequest.py
aliyunsdkiotcc/request/v20210513/CreateAuthorizationRuleRequest.py
aliyunsdkiotcc/request/v20210513/CreateAuthorizationRulesRequest.py
aliyunsdkiotcc/request/v20210513/CreateConnectionPoolRequest.py
aliyunsdkiotcc/request/v20210513/CreateDNSServiceRuleRequest.py
aliyunsdkiotcc/request/v20210513/CreateGroupAuthorizationRuleRequest.py
aliyunsdkiotcc/request/v20210513/CreateGroupDNSServiceRuleRequest.py
aliyunsdkiotcc/request/v20210513/CreateGroupIpMappingRuleRequest.py
aliyunsdkiotcc/request/v20210513/CreateIoTCloudConnectorBackhaulRouteRequest.py
aliyunsdkiotcc/request/v20210513/CreateIoTCloudConnectorGroupRequest.py
aliyunsdkiotcc/request/v20210513/CreateIoTCloudConnectorRequest.py
aliyunsdkiotcc/request/v20210513/CreateIpMappingRuleRequest.py
aliyunsdkiotcc/request/v20210513/CreateServiceEntryRequest.py
aliyunsdkiotcc/request/v20210513/CreateServiceRequest.py
aliyunsdkiotcc/request/v20210513/DeleteAuthorizationRuleRequest.py
aliyunsdkiotcc/request/v20210513/DeleteAuthorizationRulesRequest.py
aliyunsdkiotcc/request/v20210513/DeleteConnectionPoolRequest.py
aliyunsdkiotcc/request/v20210513/DeleteDNSServiceRuleRequest.py
aliyunsdkiotcc/request/v20210513/DeleteGroupAuthorizationRuleRequest.py
aliyunsdkiotcc/request/v20210513/DeleteGroupDNSServiceRuleRequest.py
aliyunsdkiotcc/request/v20210513/DeleteGroupIpMappingRuleRequest.py
aliyunsdkiotcc/request/v20210513/DeleteIoTCloudConnectorGroupRequest.py
aliyunsdkiotcc/request/v20210513/DeleteIoTCloudConnectorRequest.py
aliyunsdkiotcc/request/v20210513/DeleteIoTCloudConnetorBackhaulRouteRequest.py
aliyun_python_sdk_iotcc-2.0.7.dist-info/LICENSE
aliyun_python_sdk_iotcc-2.0.7.dist-info/METADATA
aliyun_python_sdk_iotcc-2.0.7.dist-info/WHEEL
aliyun_python_sdk_iotcc-2.0.7.dist-info/top_level.txt
aliyun_python_sdk_iotcc-2.0.7.dist-info/RECORD
